spindlex/__init__.py
spindlex/_version.py
spindlex/exceptions.py
spindlex/py.typed
spindlex/auth/__init__.py
spindlex/auth/gssapi.py
spindlex/auth/keyboard_interactive.py
spindlex/auth/password.py
spindlex/auth/publickey.py
spindlex/client/__init__.py
spindlex/client/async_sftp_client.py
spindlex/client/async_ssh_client.py
spindlex/client/sftp_client.py
spindlex/client/ssh_client.py
spindlex/crypto/__init__.py
spindlex/crypto/backend.py
spindlex/crypto/ciphers.py
spindlex/crypto/kex.py
spindlex/crypto/pkey.py
spindlex/hostkeys/__init__.py
spindlex/hostkeys/policy.py
spindlex/hostkeys/storage.py
spindlex/logging/__init__.py
spindlex/logging/formatters.py
spindlex/logging/handlers.py
spindlex/logging/logger.py
spindlex/logging/monitoring.py
spindlex/logging/sanitizer.py
spindlex/protocol/__init__.py
spindlex/protocol/constants.py
spindlex/protocol/messages.py
spindlex/protocol/sftp_constants.py
spindlex/protocol/sftp_messages.py
spindlex/protocol/utils.py
spindlex/server/__init__.py
spindlex/server/sftp_server.py
spindlex/server/ssh_server.py
spindlex/tools/__init__.py
spindlex/tools/benchmark.py
spindlex/tools/keygen.py
spindlex/transport/__init__.py
spindlex/transport/async_channel.py
spindlex/transport/async_transport.py
spindlex/transport/channel.py
spindlex/transport/forwarding.py
spindlex/transport/kex.py
spindlex/transport/transport.py
spindlex-0.2.0.dist-info/licenses/LICENSE
spindlex-0.2.0.dist-info/METADATA
spindlex-0.2.0.dist-info/WHEEL
spindlex-0.2.0.dist-info/top_level.txt
spindlex-0.2.0.dist-info/RECORD
